sparse_file/__init__.py
sparse_file/sparse_nix.py
sparse_file/sparse_win.py
sparse_file-0.0.2.dist-info/LICENSE
sparse_file-0.0.2.dist-info/METADATA
sparse_file-0.0.2.dist-info/WHEEL
sparse_file-0.0.2.dist-info/RECORD
