Metadata-Version: 2.1
Name: sparse-file
Version: 0.0.2
Summary: Python package for creating and managing sparse files.
License: MIT
Author: Michael Wilmes
Requires-Python: >=3.8
Classifier: License :: OSI Approved :: MIT License
Classifier: Programming Language :: Python :: 3
Classifier: Programming Language :: Python :: 3.8
Classifier: Programming Language :: Python :: 3.9
Classifier: Programming Language :: Python :: 3.10
Classifier: Programming Language :: Python :: 3.11
